Trojanhorse/__init__.py
Trojanhorse-1.0.dist-info/LICENSE
Trojanhorse-1.0.dist-info/METADATA
Trojanhorse-1.0.dist-info/WHEEL
Trojanhorse-1.0.dist-info/top_level.txt
Trojanhorse-1.0.dist-info/RECORD
