Metadata-Version: 2.1
Name: Trojanhorse
Version: 1.0
Summary: 木马病毒制作
Author: 王芋童
Author-email: wyt18222152539wyt@163.com
Classifier: Programming Language :: Python :: 3
Classifier: License :: OSI Approved :: MIT License
Classifier: Operating System :: OS Independent
Requires-Python: >=3
License-File: LICENSE
Requires-Dist: pyinstaller
